{
  "updated": "2025-09-12T23:18:55.703249",
  "date": "2025-09-11",
  "summary": {
    "daily_active_users": 81,
    "calculator_conversion_rate": 0,
    "platform_breakdown": {
      "iOS": 81
    },
    "total_interactions": 0
  },
  "trend": [
    {
      "date": "2025-09-05",
      "users": 109,
      "calculator_uses": 2
    },
    {
      "date": "2025-09-06",
      "users": 124,
      "calculator_uses": 0
    },
    {
      "date": "2025-09-07",
      "users": 132,
      "calculator_uses": 5
    },
    {
      "date": "2025-09-08",
      "users": 145,
      "calculator_uses": 14
    },
    {
      "date": "2025-09-09",
      "users": 98,
      "calculator_uses": 2
    },
    {
      "date": "2025-09-10",
      "users": 123,
      "calculator_uses": 0
    },
    {
      "date": "2025-09-11",
      "users": 81,
      "calculator_uses": 0
    }
  ],
  "feature_adoption_percentage": {},
  "status": "active"
}