{
  "updated": "2025-10-27T23:20:41.735799",
  "date": "2025-10-26",
  "summary": {
    "daily_active_users": 110,
    "calculator_conversion_rate": 0,
    "platform_breakdown": {
      "iOS": 110
    },
    "total_interactions": 0
  },
  "trend": [
    {
      "date": "2025-10-20",
      "users": 91,
      "calculator_uses": 0
    },
    {
      "date": "2025-10-21",
      "users": 86,
      "calculator_uses": 0
    },
    {
      "date": "2025-10-22",
      "users": 86,
      "calculator_uses": 0
    },
    {
      "date": "2025-10-23",
      "users": 77,
      "calculator_uses": 2
    },
    {
      "date": "2025-10-24",
      "users": 77,
      "calculator_uses": 0
    },
    {
      "date": "2025-10-25",
      "users": 93,
      "calculator_uses": 0
    },
    {
      "date": "2025-10-26",
      "users": 110,
      "calculator_uses": 0
    }
  ],
  "feature_adoption_percentage": {},
  "status": "active"
}