{
  "updated": "2025-07-29T23:24:49.274683",
  "date": "2025-07-28",
  "summary": {
    "daily_active_users": 161,
    "calculator_conversion_rate": 0.0,
    "platform_breakdown": {
      "iOS": 158,
      "Web": 3
    },
    "total_interactions": 0
  },
  "trend": [
    {
      "date": "2025-07-22",
      "users": 155,
      "calculator_uses": 0
    },
    {
      "date": "2025-07-23",
      "users": 177,
      "calculator_uses": 1
    },
    {
      "date": "2025-07-24",
      "users": 213,
      "calculator_uses": 0
    },
    {
      "date": "2025-07-25",
      "users": 167,
      "calculator_uses": 0
    },
    {
      "date": "2025-07-26",
      "users": 163,
      "calculator_uses": 0
    },
    {
      "date": "2025-07-27",
      "users": 156,
      "calculator_uses": 0
    },
    {
      "date": "2025-07-28",
      "users": 161,
      "calculator_uses": 0
    }
  ],
  "feature_adoption_percentage": {
    "page_view": 1.9
  },
  "status": "active"
}